{"api_api.md":"DrpzHy2M","api_index.md":"Q9oDvH_6","api_mp_math_angle.md":"BC8mLT9V","api_mp_math_const.md":"CzjBJIjC","api_mp_math_equation.md":"DEwnqiM5","api_mp_math_function.md":"BOcZ-k7E","api_mp_math_index.md":"CgPZqWk2","api_mp_math_line.md":"B9prk9Kj","api_mp_math_mp_math.md":"BMEFqLKu","api_mp_math_mp_math_typing.md":"CKmrvjJE","api_mp_math_plane.md":"CUvZ7jG1","api_mp_math_point.md":"BWtm0p2C","api_mp_math_segment.md":"Ce2Drjt_","api_mp_math_utils.md":"BLAIQYJV","api_mp_math_vector.md":"BCYHQW5q","api_particle_index.md":"DpbhbZuY","api_particle_particle.md":"Bpw0MV0e","api_presets_index.md":"CrTHQDyB","api_presets_model_index.md":"DYX4VzQJ","api_presets_model_model.md":"DNXALr2n","api_presets_presets.md":"D3vtk8sc","demo_index.md":"CVAdlaFI","en_api_api.md":"CH3w1csg","en_api_index.md":"CcTWWu9r","en_api_mp_math_angle.md":"yv5orygX","en_api_mp_math_const.md":"CwN5-LSI","en_api_mp_math_equation.md":"DwwuRd9E","en_api_mp_math_function.md":"n3_MFy8m","en_api_mp_math_index.md":"ChUIwSIA","en_api_mp_math_line.md":"CsLkFBW5","en_api_mp_math_mp_math.md":"DJS2qf3J","en_api_mp_math_mp_math_typing.md":"BR4PPCj-","en_api_mp_math_plane.md":"DjH7GwuZ","en_api_mp_math_point.md":"BWVvxLrx","en_api_mp_math_segment.md":"BE8bo5x9","en_api_mp_math_utils.md":"BTOp0Uzp","en_api_mp_math_vector.md":"BND_-HDs","en_api_particle_index.md":"_wUK3v42","en_api_particle_particle.md":"C-miN5aa","en_api_presets_index.md":"93s9NTDq","en_api_presets_model_index.md":"Dcjf9yDt","en_api_presets_model_model.md":"NeRZCRe5","en_api_presets_presets.md":"D2NLt3Ov","en_guide_index.md":"C3kI8f8A","en_index.md":"D5CddOW-","en_refer_index.md":"Cq6GWi0V","guide_index.md":"BVhQ0kPy","index.md":"DJWBRkUz","ja_api_api.md":"CUi97znf","ja_api_index.md":"Bq-UqhKm","ja_api_mp_math_angle.md":"COKT-3q5","ja_api_mp_math_const.md":"B4Hx0PDl","ja_api_mp_math_equation.md":"ByVCwmo8","ja_api_mp_math_function.md":"DOkBmQkF","ja_api_mp_math_index.md":"8LkEwDIJ","ja_api_mp_math_line.md":"qbPLxepH","ja_api_mp_math_mp_math.md":"DK0nb8oY","ja_api_mp_math_mp_math_typing.md":"CWgc3ohG","ja_api_mp_math_plane.md":"BJFpJM2I","ja_api_mp_math_point.md":"0YsozwPt","ja_api_mp_math_segment.md":"BnrDCNWp","ja_api_mp_math_utils.md":"ClIgAy7y","ja_api_mp_math_vector.md":"B4iis1R2","ja_api_particle_index.md":"CF-T1DaN","ja_api_particle_particle.md":"CViXNyfB","ja_api_presets_index.md":"B7ygl08S","ja_api_presets_model_index.md":"DQliiN_s","ja_api_presets_model_model.md":"Do2QSwoB","ja_api_presets_presets.md":"C1NN1QPM","ja_guide_index.md":"w1Tf2Adm","ja_index.md":"DnsqZi7i","ja_refer_index.md":"DamUscs8","refer_function_curry.md":"D_oqRDd3","refer_function_function.md":"Bi_82lIJ","refer_index.md":"yFZW0kI4","zht_api_api.md":"C2hNRcuq","zht_api_index.md":"BzaFnMgS","zht_api_mp_math_angle.md":"_YgAKKZ8","zht_api_mp_math_const.md":"Bg9yfrey","zht_api_mp_math_equation.md":"Dl4VlL2q","zht_api_mp_math_function.md":"DCZGszhC","zht_api_mp_math_index.md":"DKOGJ-3J","zht_api_mp_math_line.md":"Ba-cpukS","zht_api_mp_math_mp_math.md":"D_TBbvzi","zht_api_mp_math_mp_math_typing.md":"BJ_jDclm","zht_api_mp_math_plane.md":"BvA7i9gf","zht_api_mp_math_point.md":"D8L5j_3H","zht_api_mp_math_segment.md":"BA1zEcot","zht_api_mp_math_utils.md":"BxPb0JBp","zht_api_mp_math_vector.md":"EOHN-8Si","zht_api_particle_index.md":"Jrca0iMX","zht_api_particle_particle.md":"BREKhh73","zht_api_presets_index.md":"whJMVguT","zht_api_presets_model_index.md":"DqPIkHvh","zht_api_presets_model_model.md":"x1HKRue1","zht_api_presets_presets.md":"BHPziOmZ","zht_guide_index.md":"BNnMViC8","zht_index.md":"CUR8-QXm","zht_refer_index.md":"B7CQS2UW"}
